py_env/__init__.py
py_env/client.py
py_env/env.py
py_env/host.py
py_env/protocol.py
py_env/proxy_io.py
py_env/utils.py
pyenv/__init__.py
pyenv/client.py
pyenv/env.py
pyenv/host.py
pyenv/protocol.py
pyenv/proxy_io.py
pyenv/utils.py
py_env-0.0.1.dist-info/LICENSE
py_env-0.0.1.dist-info/METADATA
py_env-0.0.1.dist-info/WHEEL
py_env-0.0.1.dist-info/top_level.txt
py_env-0.0.1.dist-info/RECORD
