Metadata-Version: 2.1
Name: py-env
Version: 0.0.1
Summary: Provides persistent environment for Python 3 scripts
Home-page: https://github.com/hanayashiki/pyenv
Author: Chenyu Wang
Author-email: wangchenyu2017@gmail.com
License: UNKNOWN
Platform: UNKNOWN
Classifier: Programming Language :: Python :: 3
Classifier: License :: OSI Approved :: MIT License
Classifier: Operating System :: POSIX :: Linux 
